{
  "0e93b819cc2e8121f7281dc8e4eaaf78" : {
    "statistic" : {
      "failed" : 0,
      "broken" : 0,
      "skipped" : 0,
      "passed" : 1,
      "unknown" : 0,
      "total" : 1
    },
    "items" : [ {
      "uid" : "f769e39b283d19e",
      "reportUrl" : "https://tiramtaramta.github.io/selenium-py-peldatar/135//#testresult/f769e39b283d19e",
      "status" : "passed",
      "time" : {
        "start" : 1624960824579,
        "stop" : 1624960824580,
        "duration" : 1
      }
    } ]
  },
  "753cdf21aa3257d3e2249d83346a13e6" : {
    "statistic" : {
      "failed" : 0,
      "broken" : 0,
      "skipped" : 0,
      "passed" : 1,
      "unknown" : 0,
      "total" : 1
    },
    "items" : [ {
      "uid" : "14cea2504c8a06a9",
      "reportUrl" : "https://tiramtaramta.github.io/selenium-py-peldatar/135//#testresult/14cea2504c8a06a9",
      "status" : "passed",
      "time" : {
        "start" : 1624960824577,
        "stop" : 1624960824578,
        "duration" : 1
      }
    } ]
  },
  "77caee529814bb5616db6b28df37c87c" : {
    "statistic" : {
      "failed" : 0,
      "broken" : 0,
      "skipped" : 0,
      "passed" : 1,
      "unknown" : 0,
      "total" : 1
    },
    "items" : [ {
      "uid" : "b3587da1535b5352",
      "reportUrl" : "https://tiramtaramta.github.io/selenium-py-peldatar/135//#testresult/b3587da1535b5352",
      "status" : "passed",
      "time" : {
        "start" : 1624960824575,
        "stop" : 1624960824575,
        "duration" : 0
      }
    } ]
  },
  "0cc1fa42e1c19a0d3fd610d45c4ba65a" : {
    "statistic" : {
      "failed" : 0,
      "broken" : 0,
      "skipped" : 0,
      "passed" : 1,
      "unknown" : 0,
      "total" : 1
    },
    "items" : [ {
      "uid" : "a759444547f73a8c",
      "reportUrl" : "https://tiramtaramta.github.io/selenium-py-peldatar/135//#testresult/a759444547f73a8c",
      "status" : "passed",
      "time" : {
        "start" : 1624960824572,
        "stop" : 1624960824572,
        "duration" : 0
      }
    } ]
  }
}